vectors/__init__.py
python_vectors-1.2.3.dist-info/LICENSE
python_vectors-1.2.3.dist-info/METADATA
python_vectors-1.2.3.dist-info/WHEEL
python_vectors-1.2.3.dist-info/top_level.txt
python_vectors-1.2.3.dist-info/RECORD
