Metadata-Version: 2.1
Name: python-vectors
Version: 1.2.3
Summary: A vector library to contain and manipulate 2D and 3D points.
Home-page: https://pypi.org/project/python-vectors/
Author: Foster Reichert
Author-email: dev@fosterreichert.com
License: UNKNOWN
Platform: UNKNOWN
Classifier: Programming Language :: Python :: 3
Classifier: Operating System :: OS Independent
Requires-Python: >=3.6
